gitviz/__init__.py
gitviz/api.py
gitviz/cli.py
gitviz/dashboard.py
gitviz/exporter.py
gitviz/filters.py
gitviz/git_analyzer.py
gitviz/visualizer.py
gitviz-0.1.0.dist-info/licenses/LICENSE
tests/test_cli.py
tests/test_core.py
tests/test_dashboard.py
gitviz-0.1.0.dist-info/METADATA
gitviz-0.1.0.dist-info/WHEEL
gitviz-0.1.0.dist-info/entry_points.txt
gitviz-0.1.0.dist-info/top_level.txt
gitviz-0.1.0.dist-info/RECORD
