Metadata-Version: 2.4
Name: gitviz
Version: 0.1.0
Summary: Visualize git commits and contributions
Author-email: pravin balu bhadane <bhadanepravin4444@gamil.com>
License: MIT
Classifier: Programming Language :: Python :: 3
License-File: LICENSE
Dynamic: license-file
